tcpfeature/__init__.py
tcpfeature/__main__.py
tcpfeature-0.0.3.dist-info/LICENSE
tcpfeature-0.0.3.dist-info/METADATA
tcpfeature-0.0.3.dist-info/WHEEL
tcpfeature-0.0.3.dist-info/top_level.txt
tcpfeature-0.0.3.dist-info/RECORD
