Metadata-Version: 2.1
Name: tcpfeature
Version: 0.0.3
Summary: extraction feature from tcp/ip for machine learning
Home-page: https://github.com/pypa/tcpfeature
Author: dzokha
Author-email: dzokha1010@gmail.com
License: UNKNOWN
Platform: UNKNOWN
Classifier: Programming Language :: Python :: 3
Classifier: License :: OSI Approved :: MIT License
Classifier: Operating System :: OS Independent
